Workbook
Name Excel_BuiltIn_Print_Area_1_1: Quotation!$A$3:$M$47
Name Excel_BuiltIn_Print_Area_1_1_1: #REF!
Name Excel_BuiltIn_Print_Area_2_1: Quotation!$A$3:$M$50
Name Excel_BuiltIn_Print_Titles_1: #REF!

Sheet Quotation
E1: EC InfoTech Limited | J1: QUOTATION
E2: Unit D, 3/F, Block 2, Camel Paint Building, 62 Hoi Yuen Road, Kwun Tong, Kowloon Security License No.: 1275 Tel: 2876 2990 Fax: 3101 0616 Email: cs@ecinfohk.com Website: www.ecinfohk.com
A3: To : | K3: Date :
A4: Site : | K4: Our Ref. :
A5: Attn : | K5: You Ref. :
A6: Tel : | K6: From :
A7: E-mail : | K7: Tel :
A8: S/R No : | K8: Fax:
K9: Email:
K10: Contract No:
K11: KLN
A13: Replacement work of IP Dome Camera - CHEUNG SHA WAN DIVISIONAL POLICE STATION - 長沙灣警署
A14: Item | D14: Description | H14: Rate | I14: Net Price (HKD) | J14: Qty | K14: Unit | L14: Discount | M14: Amount (HKD)
L31: Total: | M31: =SUM(M15:M30) -> 0
A34: Terms & Conditions
A35: Payment :
A36: Validity:
A37: Delivery time:
A38: Warranty:
A41: The undersigned confirms and places order for the aforesaid. | K41: For and on behalf of EC InfoTech Limited.
K42: Prepared by:
K43: Checked by:
A45: Authorized Signature & Company Chop | K45: Name:
A46: Name: | K46: Date:
A47: Title:

Sheet Cost Sheet
C1: Ec InfoTech Limited
C2: Unit D, 3/F, Block 2, Camel Paint Building, 62 Hoi Yuen Road, Kwun Tong, Kowloon, H.K.
C3: Tel: (852) 2876 2990 Fax: (852) 3101 0616 URL: http://www.ecinfohk.com Email: cs@ecinfohk.com
A5: Cost Sheet
A7: Request by: | B7: =Quotation!M6 -> 0 | H7: Date: | I7: =Quotation!M3 -> 0 | K7: Quotation ref : | M7: =Quotation!M4 -> 0
A8: Site: | B8: =Quotation!C4 -> 0 | H8: Contract Sum : | I8: =Quotation!#REF! -> #REF! | K8: Job Completion Date:
A9: Description of project: | B9: =Quotation!#REF! -> #REF! | H9: Profit: | K9: Profit percetage:
A12: Vendor (By Purchasing Team) | B12: Sub-contractor (By Sales Team) | C12: (By Sales Team) | F12: Budgeted (by Sales Team) | I12: Actual (By Purchasing Team) | L12: Remarks | M12: Progress (P.O. No.) (By Purchasing Team) | N12: Sign By Receiver
C13: Brand | D13: Model | E13: Description | F13: Qty | G13: Unit Rate | H13: Amount (HKD) | I13: Qty | J13: Unit Rate | K13: Amount (HKD)
C14: =Quotation!#REF! -> #REF! | D14: =Quotation!#REF! -> #REF! | E14: =Quotation!#REF! -> #REF! | F14: =Quotation!#REF! -> #REF! | H14: =Quotation!#REF! -> #REF!
C15: =Quotation!#REF! -> #REF! | D15: =Quotation!#REF! -> #REF! | E15: =Quotation!#REF! -> #REF! | F15: =Quotation!#REF! -> #REF! | H15: =Quotation!#REF! -> #REF!
C16: =Quotation!#REF! -> #REF! | D16: =Quotation!#REF! -> #REF! | E16: =Quotation!#REF! -> #REF! | F16: =Quotation!#REF! -> #REF! | H16: =Quotation!#REF! -> #REF!
C17: =Quotation!#REF! -> #REF! | D17: =Quotation!#REF! -> #REF! | E17: =Quotation!#REF! -> #REF! | F17: =Quotation!#REF! -> #REF! | H17: =Quotation!#REF! -> #REF!
G34: Total: | H34: =SUM(H14:H33) -> #REF! | K34: =SUM(K14:K33) -> 0
A51: EC-SAL-001-R0

Sheet MR Form
B1: Ec InfoTech Limited
B2: Unit D, 3/F, Block 2, Camel Paint Building, 62 Hoi Yuen Road, Kwun Tong, Kowloon, H.K.
B3: Tel: (852) 2876 2990 Fax: (852) 3101 0616 URL: http://www.ecinfohk.com Email: cs@ecinfohk.com
A5: Material Requisition Form
A7: 申請人： Request by: | B7: Pang Suet Fung | F7: 合同總價： Contract Sum: | H7: =Quotation!M31 -> 0 | L7: 日期： Date: | N7: □ | O7: Maintenance (M)
A8: 場地： Site: | B8: ='Cost Sheet'!B8:D8 -> 0 | F8: 結算價格： Completion Sum: | H8: =H34 -> 11400 | L8: Quotation ref : | M8: ='Cost Sheet'!M7 -> 0 | N8: □ | O8: Project (P)
F9: 利潤： Profit: | H9: =H7-H8 -> -11400 | L9: 完成日期： Completion Date | N9: □ | O9: Internal Used (I)
A10: 工程項目： Description of project: | B10: ='Cost Sheet'!B9:D9 -> #REF! | F10: 利潤率 Profit Margin | H10: =(H7-H8)/H7 -> #DIV/0!
A12: 供應商 (由採購組填寫) Vendor (By Purchasing Team) | B12: 判頭 (由銷售組填寫) Sub-contractor (By Sales Team) | C12: 由銷售組填寫 By Sales Team | F12: 預計成本 (由銷售組填寫) Budgeted cost (By Sales Team) | I12: 備註 (由銷售組填寫) Remarks (By Sales Team) | J12: 實際成本 (由採購組填寫) Actual cost (By Purchasing Team) | M12: 備註 (由採購組填寫) Remarks (By Purchasing Team) | N12: 進度 (採購單號) (由採購組填寫) Progress (P.O. No.) (By Purchasing Team) | O12: 採購單發票日期 PO Invoice Date
C13: 牌子 Brand | D13: 型號 Model | E13: 內容 Description | F13: 數量 Quantity | G13: 單位價格 Unit Rate | H13: 合計 (港幣) Amount (HKD) | J13: 數量 Quantity | K13: 單位價格 Unit Rate | L13: 合計 (港幣) Amount (HKD)
A14: 0 | B14: 0 | C14: DISS | D14: DI-F1200 | E14: Camera | F14: 3 | G14: 3800 | H14: =F14*G14 -> 11400
A15: 0 | B15: 0
A16: 0 | B16: 0
A17: 0 | B17: 0
A18: 0 | B18: 0
A19: 0 | B19: 0
A20: 0 | B20: 0
A21: 0 | B21: 0
A22: 0 | B22: 0
A23: 0 | B23: 0
A24: 0 | B24: 0
A25: 0 | B25: 0
A26: 0 | B26: 0
... A32: 0 | B32: 0
G34: 合計 Total: | H34: =SUM(H14:H33) -> 11400 | K34: 合計 Total: | L34: =SUM(L14:L33) -> 0
G36: Budget Prepared By (Sales Team): | M36: Actual Cost Prepared By (Purchasing Team):
H37: Name and Signature | N37: Name and Signature
G39: Budget Approved By: (Sales Team Leader) | M39: Actual Cost Approved By: (Sales Team Leader)
H40: Name and Signature | N40: Name and Signature
